ament_cmake_version/_dummy.cpython-310-x86_64-linux-gnu.so
ros_ament_cmake_version-2.7.3.data/data/share/ament_cmake_version/local_setup.bash
ros_ament_cmake_version-2.7.3.data/data/share/ament_cmake_version/local_setup.dsv
ros_ament_cmake_version-2.7.3.data/data/share/ament_cmake_version/local_setup.sh
ros_ament_cmake_version-2.7.3.data/data/share/ament_cmake_version/local_setup.zsh
ros_ament_cmake_version-2.7.3.data/data/share/ament_cmake_version/package.dsv
ros_ament_cmake_version-2.7.3.data/data/share/ament_cmake_version/package.xml
ros_ament_cmake_version-2.7.3.data/data/share/ament_cmake_version/cmake/ament_cmake_version-extras.cmake
ros_ament_cmake_version-2.7.3.data/data/share/ament_cmake_version/cmake/ament_cmake_versionConfig-version.cmake
ros_ament_cmake_version-2.7.3.data/data/share/ament_cmake_version/cmake/ament_cmake_versionConfig.cmake
ros_ament_cmake_version-2.7.3.data/data/share/ament_cmake_version/cmake/ament_export_development_version_if_higher_than_manifest.cmake
ros_ament_cmake_version-2.7.3.data/data/share/ament_cmake_version/environment/ament_prefix_path.dsv
ros_ament_cmake_version-2.7.3.data/data/share/ament_cmake_version/environment/ament_prefix_path.sh
ros_ament_cmake_version-2.7.3.data/data/share/ament_cmake_version/environment/path.dsv
ros_ament_cmake_version-2.7.3.data/data/share/ament_cmake_version/environment/path.sh
ros_ament_cmake_version-2.7.3.data/data/share/ament_index/resource_index/package_run_dependencies/ament_cmake_version
ros_ament_cmake_version-2.7.3.data/data/share/ament_index/resource_index/packages/ament_cmake_version
ros_ament_cmake_version-2.7.3.data/data/share/ament_index/resource_index/parent_prefix_path/ament_cmake_version
ros_ament_cmake_version-2.7.3.dist-info/METADATA
ros_ament_cmake_version-2.7.3.dist-info/WHEEL
ros_ament_cmake_version-2.7.3.dist-info/top_level.txt
ros_ament_cmake_version-2.7.3.dist-info/RECORD
