Metadata-Version: 2.4
Name: ros-ament-cmake-version
Version: 2.7.3
Summary: Wheel for the ament_cmake_version (ros-ament-cmake-version) ROS 2 package.
Dynamic: description
Dynamic: description-content-type
Dynamic: summary
